trytond/modules/health_lab/COPYING
trytond/modules/health_lab/README.rst
trytond/modules/health_lab/__init__.py
trytond/modules/health_lab/data/gnuhealth_commands.xml
trytond/modules/health_lab/data/health_lab_sequences.xml
trytond/modules/health_lab/data/lab_test_data.xml
trytond/modules/health_lab/data/messages/messages.xml
trytond/modules/health_lab/exceptions.py
trytond/modules/health_lab/health_lab.py
trytond/modules/health_lab/health_lab_report.xml
trytond/modules/health_lab/health_lab_view.xml
trytond/modules/health_lab/icons/execute_icon.svg
trytond/modules/health_lab/icons/lab_icon.svg
trytond/modules/health_lab/locale/ar.po
trytond/modules/health_lab/locale/de.po
trytond/modules/health_lab/locale/el.po
trytond/modules/health_lab/locale/eo.po
trytond/modules/health_lab/locale/es.po
trytond/modules/health_lab/locale/fr.po
trytond/modules/health_lab/locale/health_lab.pot
trytond/modules/health_lab/locale/it_IT.po
trytond/modules/health_lab/locale/ja_JP.po
trytond/modules/health_lab/locale/ka.po
trytond/modules/health_lab/locale/lo.po
trytond/modules/health_lab/locale/pt_BR.po
trytond/modules/health_lab/locale/sv.po
trytond/modules/health_lab/locale/tr.po
trytond/modules/health_lab/locale/uk.po
trytond/modules/health_lab/locale/zh_CN.po
trytond/modules/health_lab/pyproject.toml
trytond/modules/health_lab/report/labtest_report.fodt
trytond/modules/health_lab/security/access_rights.xml
trytond/modules/health_lab/sequences.py
trytond/modules/health_lab/tests/__init__.py
trytond/modules/health_lab/tests/test_health_lab.py
trytond/modules/health_lab/tryton.cfg
trytond/modules/health_lab/view/gnuhealth_lab.xml
trytond/modules/health_lab/view/gnuhealth_lab_test.xml
trytond/modules/health_lab/view/gnuhealth_lab_test_request_form.xml
trytond/modules/health_lab/view/gnuhealth_lab_test_request_tree.xml
trytond/modules/health_lab/view/gnuhealth_lab_test_tree.xml
trytond/modules/health_lab/view/gnuhealth_lab_tree.xml
gnuhealth_lab-5.0.2.dist-info/METADATA
gnuhealth_lab-5.0.2.dist-info/WHEEL
gnuhealth_lab-5.0.2.dist-info/licenses/COPYING
gnuhealth_lab-5.0.2.dist-info/RECORD
